ccentral/__init__.py
ccentral/client.py
ccentral/tests/__init__.py
ccentral/tests/test_client.py
ccentral-0.4.1.dist-info/LICENSE
ccentral-0.4.1.dist-info/METADATA
ccentral-0.4.1.dist-info/WHEEL
ccentral-0.4.1.dist-info/top_level.txt
ccentral-0.4.1.dist-info/RECORD
