Metadata-Version: 2.1
Name: ccentral
Version: 0.4.1
Summary: CCentral client library
Home-page: https://github.com/slvwolf/python-ccentral
Author: Santtu Järvi
Author-email: santtu.jarvi@finfur.net
License: UNKNOWN
Platform: UNKNOWN
Classifier: Programming Language :: Python :: 3
Classifier: License :: OSI Approved :: MIT License
Classifier: Operating System :: OS Independent
Classifier: Topic :: System :: Monitoring
Classifier: Development Status :: 5 - Production/Stable
Requires-Python: >=3.6
Requires-Dist: pyformance (>=0.4.0)
Requires-Dist: python-etcd (==0.4.5)
